wordlehelper/__init__.py
wordlehelper/words.py
py_wordle_helper-0.0.1.dist-info/LICENSE.txt
py_wordle_helper-0.0.1.dist-info/METADATA
py_wordle_helper-0.0.1.dist-info/WHEEL
py_wordle_helper-0.0.1.dist-info/entry_points.txt
py_wordle_helper-0.0.1.dist-info/top_level.txt
py_wordle_helper-0.0.1.dist-info/RECORD
